genice2_mdanalysis/__init__.py
genice2_mdanalysis/formats/__init__.py
genice2_mdanalysis/formats/mdanalysis.py
genice2_mdanalysis-0.7.dist-info/METADATA
genice2_mdanalysis-0.7.dist-info/WHEEL
genice2_mdanalysis-0.7.dist-info/entry_points.txt
genice2_mdanalysis-0.7.dist-info/RECORD
