Metadata-Version: 2.1
Name: genice2-mdanalysis
Version: 0.7
Summary: A GenIce format plugin to make a Universe of MDAnalysis.
License: MIT
Author: vitroid
Author-email: vitroid@gmail.com
Requires-Python: >=3.9,<4.0
Classifier: License :: OSI Approved :: MIT License
Classifier: Programming Language :: Python :: 3
Classifier: Programming Language :: Python :: 3.9
Classifier: Programming Language :: Python :: 3.10
Classifier: Programming Language :: Python :: 3.11
Classifier: Programming Language :: Python :: 3.12
Requires-Dist: GenIce2 (>=2.2.5.2,<3.0.0.0)
Requires-Dist: MDAnalysis
